grilled/algorithm/__init__.py
grilled_algorithm-0.1.8.dist-info/WHEEL
grilled_algorithm-0.1.8.dist-info/METADATA
grilled_algorithm-0.1.8.dist-info/RECORD
