Metadata-Version: 2.1
Name: grilled-algorithm
Version: 0.1.8
Summary: 
Author: hans
Author-email: dxzenghan@163.com
Requires-Python: >=3.7,<4.0
Classifier: Programming Language :: Python :: 3
Classifier: Programming Language :: Python :: 3.7
Classifier: Programming Language :: Python :: 3.8
Classifier: Programming Language :: Python :: 3.9
Requires-Dist: grilled-common (>=0.2.1,<0.3.0)
Requires-Dist: pandas (>=1.2.3,<2.0.0)
Requires-Dist: python-dotenv (>=0.16.0,<0.17.0)
